wps_remote-2.15.0.dist-info/METADATA
wps_remote-2.15.0.dist-info/RECORD
wps_remote-2.15.0.dist-info/WHEEL
wps_remote-2.15.0.dist-info/top_level.txt
wpsremote/ConfigParser.py
wpsremote/__init__.py
wpsremote/action.py
wpsremote/bus.py
wpsremote/busIndipendentMessages.py
wpsremote/command_line_parameter.py
wpsremote/computation_job_const.py
wpsremote/computation_job_input.py
wpsremote/computation_job_inputs.py
wpsremote/computation_job_param.py
wpsremote/computational_job_input_action.py
wpsremote/computational_job_input_action_cmd_param.py
wpsremote/computational_job_input_action_copyfile.py
wpsremote/computational_job_input_action_create_json_file.py
wpsremote/computational_job_input_action_update_ini_file.py
wpsremote/computational_job_input_action_update_json_file.py
wpsremote/computational_job_input_actions.py
wpsremote/configInstance.py
wpsremote/config_file_parameter.py
wpsremote/config_file_parameter_cmre_oaa.py
wpsremote/decryptor.py
wpsremote/encryptor.py
wpsremote/ftpUpload.py
wpsremote/ftpsUpload.py
wpsremote/input_parameter.py
wpsremote/input_parameters.py
wpsremote/introspection.py
wpsremote/mockutils.py
wpsremote/output_file_parameter.py
wpsremote/output_parameters.py
wpsremote/path.py
wpsremote/process_test.py
wpsremote/processbot.py
wpsremote/resource_cleaner.py
wpsremote/resource_monitor.py
wpsremote/serviceTester.py
wpsremote/servicebot.py
wpsremote/sftpUpload.py
wpsremote/termination_handler.py
wpsremote/upload.py
wpsremote/wpsagent.py
wpsremote/xmppBus.py
wpsremote/xmppMessages.py
wpsremote/xmpp_data/service.log
wpsremote/xmpp_data/configs/logger.properties
wpsremote/xmpp_data/configs/remote.config
wpsremote/xmpp_data/configs/myservice/logger.properties
wpsremote/xmpp_data/configs/myservice/service.config
wpsremote/xmpp_data/configs/myservice/service.config.bak
wpsremote/xmpp_data/configs/myservice/code/logger_test.properties
wpsremote/xmpp_data/configs/myservice/code/test.py
wpsremote/xmpp_data/output/contour.zip
wpsremote/xmpp_data/output/contour_0dc7b2bd-e605.dbf
wpsremote/xmpp_data/output/contour_0dc7b2bd-e605.prj
