Metadata-Version: 2.1
Name: wps-remote
Version: 2.15.0
Summary: A library that allows users to publish their executables as GeoServer WPS Processes through the XMPP protocol
Home-page: https://github.com/geoserver/wps-remote
Author: GeoServer Developers
Author-email: geoserver-devel@lists.sourceforge.net
License: GPL
Keywords: XMPP Beckend for GeoServer Remote WPS ProcessFactory.
Platform: UNKNOWN
Classifier: Environment :: Web Environment
Classifier: License :: OSI Approved :: GNU General Public License v2 (GPLv2)
Classifier: Intended Audience :: Developers
Classifier: Intended Audience :: Science/Research
Classifier: Operating System :: OS Independent
Classifier: Programming Language :: Python
Classifier: Topic :: Scientific/Engineering :: GIS
Requires-Dist: astroid (==1.4.4)
Requires-Dist: colorama (==0.3.6)
Requires-Dist: flake8 (==2.5.4)
Requires-Dist: functools32
Requires-Dist: jsonschema (==2.5.1)
Requires-Dist: lazy-object-proxy (==1.2.1)
Requires-Dist: mccabe (==0.4.0)
Requires-Dist: paramiko
Requires-Dist: pep8 (==1.7.0)
Requires-Dist: psutil (>=4.0.0)
Requires-Dist: pycrypto
Requires-Dist: pyflakes (==1.0.0)
Requires-Dist: pylint (==1.5.4)
Requires-Dist: six (==1.10.0)
Requires-Dist: sleekxmpp (>=1.3.1)
Requires-Dist: wheel (==0.24.0)
Requires-Dist: wrapt (==1.10.10)
